xml_extractor/Main.py
xml_extractor/__init__.py
xml_extractor/constants.py
xml_extractor-0.0.1.dist-info/LICENSE
xml_extractor-0.0.1.dist-info/METADATA
xml_extractor-0.0.1.dist-info/WHEEL
xml_extractor-0.0.1.dist-info/top_level.txt
xml_extractor-0.0.1.dist-info/RECORD
