Metadata-Version: 2.1
Name: xml-extractor
Version: 0.0.1
Summary: Package made to extract xml structures for easier analysis
Home-page: https://github.com/pypa/sampleproject
Author: Pedro Cardouzo
Author-email: pedro.cardouzo@sap.com
License: UNKNOWN
Platform: UNKNOWN
Classifier: Programming Language :: Python :: 3
Classifier: License :: OSI Approved :: MIT License
Classifier: Operating System :: OS Independent
